aws_json_term_matcher/__init__.py
aws_json_term_matcher/exceptions.py
aws_json_term_matcher/grammar.lark
aws_json_term_matcher/matcher.py
aws_json_term_matcher-0.1.5.dist-info/LICENSE
aws_json_term_matcher-0.1.5.dist-info/METADATA
aws_json_term_matcher-0.1.5.dist-info/WHEEL
aws_json_term_matcher-0.1.5.dist-info/top_level.txt
aws_json_term_matcher-0.1.5.dist-info/RECORD
